bhdownloader/__init__.py
bhdownloader/cli.py
bhdownloader/core.py
bhdownloader/py.typed
bhdownloader-1.1.0.dist-info/LICENSE
bhdownloader-1.1.0.dist-info/METADATA
bhdownloader-1.1.0.dist-info/WHEEL
bhdownloader-1.1.0.dist-info/entry_points.txt
bhdownloader-1.1.0.dist-info/top_level.txt
bhdownloader-1.1.0.dist-info/RECORD
