Metadata-Version: 2.2
Name: bhdownloader
Version: 1.1.0
Summary: A fast and simple downloader for BuzzHeavier and FuckingFast file hosting services
Author: BHDownloader Contributors
License: MIT
Project-URL: Homepage, https://github.com/bhdownloader/bhdownloader
Project-URL: Documentation, https://github.com/bhdownloader/bhdownloader#readme
Project-URL: Repository, https://github.com/bhdownloader/bhdownloader
Project-URL: Issues, https://github.com/bhdownloader/bhdownloader/issues
Keywords: downloader,buzzheavier,fuckingfast,file-hosting,cli,download-manager
Classifier: Development Status :: 5 - Production/Stable
Classifier: Environment :: Console
Classifier: Intended Audience :: End Users/Desktop
Classifier: Intended Audience :: Developers
Classifier: Operating System :: OS Independent
Classifier: Programming Language :: Python :: 3
Classifier: Programming Language :: Python :: 3.8
Classifier: Programming Language :: Python :: 3.9
Classifier: Programming Language :: Python :: 3.10
Classifier: Programming Language :: Python :: 3.11
Classifier: Programming Language :: Python :: 3.12
Classifier: Topic :: Internet :: WWW/HTTP
Classifier: Topic :: Utilities
Requires-Python: >=3.8
License-File: LICENSE
Requires-Dist: requests>=2.25.0
Requires-Dist: beautifulsoup4>=4.9.0
Requires-Dist: tqdm>=4.60.0
Provides-Extra: dev
Requires-Dist: pytest>=7.0.0; extra == "dev"
Requires-Dist: pytest-cov>=4.0.0; extra == "dev"
Requires-Dist: black>=23.0.0; extra == "dev"
Requires-Dist: isort>=5.0.0; extra == "dev"
Requires-Dist: mypy>=1.0.0; extra == "dev"
Requires-Dist: types-requests; extra == "dev"
Requires-Dist: types-beautifulsoup4; extra == "dev"
Requires-Dist: types-tqdm; extra == "dev"
